archminer/__about__.py
archminer/__init__.py
archminer/cli.py
archminer/layout.py
archminer-1.1.0.dist-info/METADATA
archminer-1.1.0.dist-info/WHEEL
archminer-1.1.0.dist-info/entry_points.txt
archminer-1.1.0.dist-info/licenses/LICENSE.txt
archminer-1.1.0.dist-info/RECORD
