Metadata-Version: 2.1
Name: archminer
Version: 1.1.0
Project-URL: Documentation, https://github.com/LeidenUniversityLibrary/archminer#readme
Project-URL: Issues, https://github.com/LeidenUniversityLibrary/archminer/issues
Project-URL: Source, https://github.com/LeidenUniversityLibrary/archminer
Author-email: Ben Companjen <ben@companjen.name>
License-File: LICENSE.txt
Classifier: Development Status :: 4 - Beta
Classifier: Programming Language :: Python
Classifier: Programming Language :: Python :: 3.7
Classifier: Programming Language :: Python :: 3.8
Classifier: Programming Language :: Python :: 3.9
Classifier: Programming Language :: Python :: 3.10
Classifier: Programming Language :: Python :: 3.11
Classifier: Programming Language :: Python :: Implementation :: CPython
Classifier: Programming Language :: Python :: Implementation :: PyPy
Requires-Python: >=3.7
Requires-Dist: click
Requires-Dist: pdfminer-six>=20220524
